qlapi/__init__.py
qlapi/base.py
qlapi/nrsdk.py
qlapi/paradigm.py
qlapi/rsa.py
qlapi/lib/QLNRSdk.dll
qlapi/recorder/__init__.py
qlapi/stimulator/__init__.py
qlapi/stimulator/mcf_reader.py
qlapi-0.1.5.1.dist-info/LICENSE.txt
qlapi-0.1.5.1.dist-info/METADATA
qlapi-0.1.5.1.dist-info/WHEEL
qlapi-0.1.5.1.dist-info/top_level.txt
qlapi-0.1.5.1.dist-info/RECORD
